{
    "name": "Inkwell - Light",
    "blur_strength": 2,
    "main_text_color": "rgba(62, 39, 35, 1)",
    "italics_text_color": "rgba(121, 85, 72, 1)",
    "underline_text_color": "rgba(62, 39, 35, 1)",
    "quote_text_color": "rgba(160, 82, 45, 1)",
    "blur_tint_color": "rgba(227, 212, 185, 1)",
    "chat_tint_color": "rgba(227, 212, 185, 1)",
    "user_mes_blur_tint_color": "rgba(227, 212, 185, 1)",
    "bot_mes_blur_tint_color": "rgba(227, 212, 185, 1)",
    "shadow_color": "rgba(47, 45, 59, 0.49)",
    "shadow_width": 1,
    "border_color": "rgba(130, 127, 116, 1)",
    "font_scale": 1,
    "fast_ui_mode": false,
    "waifuMode": false,
    "avatar_style": 2,
    "chat_display": 0,
    "toastr_position": "toast-top-center",
    "noShadows": true,
    "chat_width": 50,
    "timer_enabled": false,
    "timestamps_enabled": true,
    "timestamp_model_icon": false,
    "mesIDDisplay_enabled": true,
    "hideChatAvatars_enabled": true,
    "message_token_count_enabled": false,
    "expand_message_actions": false,
    "enableZenSliders": false,
    "enableLabMode": false,
    "hotswap_enabled": true,
    "custom_css": "@import url('https://fonts.googleapis.com/css2?family=Inter:ital,opsz,wght@0,14..32,100..900;1,14..32,100..900&family=JetBrains+Mono:ital,wght@0,100..800;1,100..800&family=Literata:ital,opsz,wght@0,7..72,200..900;1,7..72,200..900&display=swap');\n\n* {\n    border-radius: 0 !important; /* Fuck border-radius */\n}\n\n/* Variables */\n:root {\n\t/* Fonts */\n    --mainFontFamily: \"Inter\", sans-serif;\n    --serifFontFamily: \"Literata\", serif;\n    --monoFontFamily: \"JetBrains Mono\", monospace;\n\t\n\t/* Colors */\n\t--quoteThemeColor: #151515;\n\t--linkThemeColor: #2161a0;\n    --black30a: rgba(0, 0, 0, 0.05);\n    --golden: #DC143C;\n}\n\n/* Extension Manager Variables */\n.stem--tabUi {\n  --primaryBgColRgb: var(--primaryBgCol);\n  --bgColor: var(--SmartThemeBlurTintColor);\n  --accentColor: var(--SmartThemeQuoteColor);\n}\n\n/* Fonts */\nbody {\n    font-family: var(--mainFontFamily), sans-serif;\n}\n\ncode {\n    font-family: var(--monoFontFamily), monospaced;\n    font-size: 0.9rem;\n}\n\n/* General UI */\n.red_button {\n    color: var(--SmartThemeBlurTintColor);\n}\n\n#extensions_settings .inline-drawer-toggle.inline-drawer-header,\n#extensions_settings2 .inline-drawer-toggle.inline-drawer-header,\n#user-settings-block h4,\n.standoutHeader {\n\tbackground: none;\n\tborder: none;\n}\n\n.drawer-content {\n\tpadding: 1em;\n\tborder: none;\n}\n\n.fillLeft, .fillRight {\n\tmax-height: 100%;\n}\n\n.chatMessage {\n\tfont-family: var(--serifFontFamily), serif;\n    font-size: 1rem;\n}\n\n.mes_button {\n    filter: none;\n}\n\n.mes_text {\n\tfont-family: var(--serifFontFamily), serif;\n    font-size: 1rem;\n    line-height: 1.4rem;\n}\n\n.mes_text blockquote{\n\tpadding: 1em;\n\tmargin: 1em 0;\n}\n\n.mes_text a {\n\tcolor: var(--linkThemeColor);\n\ttext-decoration: underline;\n}\n\n.mes_text a:hover {\n\tcolor: var(--linkThemeColor);\n\ttext-decoration: none;\n}\n\n.mes_text hr {\n\tbackground-image: none;\n\tborder: 1px solid var(--SmartThemeBodyColor);\n\tmargin: 1em 2em;;\n\topacity: 0.7;\n}\n\n.mes_reasoning_header {\n    background: var(--SmartThemeChatTintColor);\n    border: 1px solid var(--SmartThemeBorderColor);;\n}\n\n.mes_reasoning {\n    font-family: var(--serifFontFamily);\n    font-size: 1rem;\n}\n\n.mes_edit_cancel.menu_button {\n    color: var(--SmartThemeBlurTintColor);\n}\n\n.mes_edit_done.menu_button {\n    color: var(--SmartThemeBlurTintColor);\n}\n\n.timestamp {\n    font-size: 0.8rem;\n}\n\n.edit_textarea {\n    background-color: var(--black30a);\n}\n\n#send_form {\n    border: none;\n}\n\n#completion_prompt_manager .completion_prompt_manager_header_advanced span {\n    filter: none;\n}\n\n#completion_prompt_manager .completion_prompt_manager_header {\n    color: var(--SmartThemeBodyColor);\n}\n\n#completion_prompt_manager #completion_prompt_manager_list .completion_prompt_manager_prompt_disabled .completion_prompt_manager_prompt_name,\n#completion_prompt_manager #completion_prompt_manager_list .completion_prompt_manager_prompt_disabled .completion_prompt_manager_prompt_name .prompt-manager-inspect-action {\n    color: var(--black50a);\n}\n\n#completion_prompt_manager #completion_prompt_manager_list li.completion_prompt_manager_prompt span span span {\n    filter: none;\n}\n\n#completion_prompt_manager #completion_prompt_manager_list .completion_prompt_manager_prompt .completion_prompt_manager_prompt_name .fa-solid {\n    color: var(--black50a);\n}\n\n.popup {\n    box-shadow: none;\n}\n\n.menu_button.popup-button-ok {\n    color: var(--SmartThemeChatTintColor);\n}\n\n.menu_button.popup-button-ok:hover {\n    color: var(--SmartThemeBodyColor);\n}\n\n/* Character Drawer */\n#bulkTagsList,\n#tagList .tag,\n#groupTagList .tag {\n    opacity: 1;\n    border: none;\n}\n\n/* Background Image */\n#bg1 {\n    filter: blur(var(--SmartThemeBlurStrength));\n    opacity: 0.5;\n}\n\n/* Extension Manager */\n.stem--tabUi .stem--tabRow .stem--tab.stem--isSelected {\n\tborder: 1px solid var(--SmartThemeBodyColor);\n}\n\n.stem--tabUi .stem--tabRow .stem--tab.stem--isSelected {\n\tborder-bottom-color: var(--bgColor);\n}\n\n.stem--tabUi .stem--tabRow .stem--tab.stem--isSelected::after {\n\tbackground: none;\n}\n\n.stem--tabUi .stem--tabRow .stem--tab.stem--isSelected::before{\n\tbackground: none;\n}\n\n/* Top Bar */\n#extensionTopBar {\n\tborder: none !important;\n\tfont-size: 1rem;\n}\n\n#top-bar {\n    box-shadow: none;\n}\n\n/* World Info Info */\n.stwii--trigger {\n\tz-index: 0 !important;\n}\n",
    "bogus_folders": true,
    "zoomed_avatar_magnification": false,
    "reduced_motion": false,
    "compact_input_area": true,
    "show_swipe_num_all_messages": false,
    "click_to_edit": false,
    "media_display": "gallery"
}